<?xml version="1.0" encoding="utf-8" standalone="no"?>
<docDocx>
 <outputPath>C:/Users/User/Desktop/api_qt_docx/example/output/ejemplo.docx</outputPath>
 <pageSetUp>
  <sizeWidth>210</sizeWidth>
  <sizeHeight>297</sizeHeight>
  <marTop>20</marTop>
  <marLeft>30</marLeft>
  <marRight>20</marRight>
  <marBottom>20</marBottom>
 </pageSetUp>
 <header>
  <image>
   <imgPath>C:/Users/User/Desktop/api_qt_docx/example/resources/img/logoUTN.png</imgPath>
   <imgHeight>92</imgHeight>
   <imgWidth>414</imgWidth>
   <imgAnchor>paralel</imgAnchor>
   <imgAlign>left</imgAlign>
  </image>
  <text>
   <content><![CDATA[Autor: Nicolas Almaraz]]></content>
   <size>11</size>
   <font>Calibri</font>
   <align>right</align>
   <underline>0</underline>
   <bold>0</bold>
   <italic>0</italic>
   <strikethrough>0</strikethrough>
   <bkgColor>FFFFFF</bkgColor>
   <fillColor>000000</fillColor>
  </text>
 </header>
 <footer>
  <text>
   <content><![CDATA[Aguante San Lorenzo!]]></content>
   <size>11</size>
   <font>Calibri</font>
   <align>left</align>
   <underline>0</underline>
   <bold>0</bold>
   <italic>0</italic>
   <strikethrough>0</strikethrough>
   <bkgColor>FFFFFF</bkgColor>
   <fillColor>000000</fillColor>
  </text>
 </footer>
 <text>
  <content><![CDATA[La Gloriosa Hinchada de San Lorenzo]]></content>
  <size>15</size>
  <font>Calibri</font>
  <align>center</align>
  <underline>1</underline>
  <bold>1</bold>
  <italic>0</italic>
  <strikethrough>0</strikethrough>
  <bkgColor>FFFFFF</bkgColor>
  <fillColor>0000FF</fillColor>
 </text>
 <text>
  <content><![CDATA[El club atletico San Lorenzo de Almagro tiene la mejor hinchada del mundo. Tiene las mejores canciones que se puedan imaginar. A continuacion adjunto una imagen para que vean]]></content>
  <size>13</size>
  <font>Calibri</font>
  <align>left</align>
  <underline>0</underline>
  <bold>0</bold>
  <italic>0</italic>
  <strikethrough>0</strikethrough>
  <bkgColor>FFFFFF</bkgColor>
  <fillColor>000000</fillColor>
 </text>
 <text>
  <content><![CDATA[Imagen de la hinchada]]></content>
  <size>14</size>
  <font>Calibri</font>
  <align>left</align>
  <underline>1</underline>
  <bold>0</bold>
  <italic>1</italic>
  <strikethrough>0</strikethrough>
  <bkgColor>FFFFFF</bkgColor>
  <fillColor>000000</fillColor>
 </text>
 <image>
  <imgPath>C:/Users/User/Desktop/api_qt_docx/example/resources/img/hinchada.jpg</imgPath>
  <imgHeight>280</imgHeight>
  <imgWidth>716</imgWidth>
  <imgAnchor>none</imgAnchor>
  <imgAlign>center</imgAlign>
 </image>
 <text>
  <content><![CDATA[Mejores canciones:]]></content>
  <size>14</size>
  <font>Calibri</font>
  <align>left</align>
  <underline>1</underline>
  <bold>0</bold>
  <italic>1</italic>
  <strikethrough>0</strikethrough>
  <bkgColor>FFFFFF</bkgColor>
  <fillColor>000000</fillColor>
 </text>
 <list>
  <element>
   <text>
    <content><![CDATA[La mas fiel]]></content>
    <size>13</size>
    <font>Calibri</font>
    <align>left</align>
    <underline>0</underline>
    <bold>0</bold>
    <italic>0</italic>
    <strikethrough>0</strikethrough>
    <bkgColor>FFFFFF</bkgColor>
    <fillColor>0000FF</fillColor>
   </text>
  </element>
  <element>
   <text>
    <content><![CDATA[Vamos ciclon, vamos a ganar]]></content>
    <size>13</size>
    <font>Calibri</font>
    <align>left</align>
    <underline>0</underline>
    <bold>0</bold>
    <italic>0</italic>
    <strikethrough>0</strikethrough>
    <bkgColor>FFFFFF</bkgColor>
    <fillColor>FF0000</fillColor>
   </text>
  </element>
  <element>
   <text>
    <content><![CDATA[Yo soy del barrio de Boedo]]></content>
    <size>13</size>
    <font>Calibri</font>
    <align>left</align>
    <underline>0</underline>
    <bold>0</bold>
    <italic>0</italic>
    <strikethrough>0</strikethrough>
    <bkgColor>FFFFFF</bkgColor>
    <fillColor>0000FF</fillColor>
   </text>
  </element>
  <element>
   <text>
    <content><![CDATA[Vamos San Lorenzo te voy a aletar]]></content>
    <size>13</size>
    <font>Calibri</font>
    <align>left</align>
    <underline>0</underline>
    <bold>0</bold>
    <italic>0</italic>
    <strikethrough>0</strikethrough>
    <bkgColor>FFFFFF</bkgColor>
    <fillColor>FF0000</fillColor>
   </text>
  </element>
  <element>
   <text>
    <content><![CDATA[Hay una cosa que nunca van a entender]]></content>
    <size>13</size>
    <font>Calibri</font>
    <align>left</align>
    <underline>0</underline>
    <bold>0</bold>
    <italic>0</italic>
    <strikethrough>0</strikethrough>
    <bkgColor>FFFFFF</bkgColor>
    <fillColor>0000FF</fillColor>
   </text>
  </element>
 </list>
 <text>
  <content><![CDATA[Estadio:]]></content>
  <size>14</size>
  <font>Calibri</font>
  <align>left</align>
  <underline>1</underline>
  <bold>0</bold>
  <italic>1</italic>
  <strikethrough>0</strikethrough>
  <bkgColor>FFFFFF</bkgColor>
  <fillColor>000000</fillColor>
 </text>
 <table>
  <columns>3</columns>
  <rows>3</rows>
  <element col="1" row="0">
   <text>
    <content><![CDATA[Platea Sur]]></content>
    <size>11</size>
    <font>Calibri</font>
    <align>left</align>
    <underline>0</underline>
    <bold>0</bold>
    <italic>0</italic>
    <strikethrough>0</strikethrough>
    <bkgColor>FFFFFF</bkgColor>
    <fillColor>000000</fillColor>
   </text>
  </element>
  <element col="1" row="2">
   <text>
    <content><![CDATA[Platea Norte]]></content>
    <size>11</size>
    <font>Calibri</font>
    <align>left</align>
    <underline>0</underline>
    <bold>0</bold>
    <italic>0</italic>
    <strikethrough>0</strikethrough>
    <bkgColor>FFFFFF</bkgColor>
    <fillColor>000000</fillColor>
   </text>
  </element>
  <element col="1" row="1">
   <text>
    <content><![CDATA[Campo de juego]]></content>
    <size>11</size>
    <font>Calibri</font>
    <align>left</align>
    <underline>0</underline>
    <bold>0</bold>
    <italic>0</italic>
    <strikethrough>0</strikethrough>
    <bkgColor>FFFFFF</bkgColor>
    <fillColor>000000</fillColor>
   </text>
  </element>
  <element col="0" row="1">
   <text>
    <content><![CDATA[Popular Local]]></content>
    <size>11</size>
    <font>Calibri</font>
    <align>left</align>
    <underline>0</underline>
    <bold>0</bold>
    <italic>0</italic>
    <strikethrough>0</strikethrough>
    <bkgColor>FFFFFF</bkgColor>
    <fillColor>000000</fillColor>
   </text>
  </element>
  <element col="2" row="1">
   <text>
    <content><![CDATA[Popular Visitante]]></content>
    <size>11</size>
    <font>Calibri</font>
    <align>left</align>
    <underline>0</underline>
    <bold>0</bold>
    <italic>0</italic>
    <strikethrough>0</strikethrough>
    <bkgColor>FFFFFF</bkgColor>
    <fillColor>000000</fillColor>
   </text>
  </element>
 </table>
</docDocx>
